MANIFEST.in
README.rst
setup.py
django_formhelper.egg-info/PKG-INFO
django_formhelper.egg-info/SOURCES.txt
django_formhelper.egg-info/dependency_links.txt
django_formhelper.egg-info/top_level.txt
formhelper/__init__.py
formhelper/apps.py
formhelper/static/formhelper/js/formsets.js
formhelper/templates/formhelper/.error_list.html.swp
formhelper/templates/formhelper/.field.html.swp
formhelper/templates/formhelper/error_list.html
formhelper/templates/formhelper/field.html
formhelper/templates/formhelper/form.html
formhelper/templates/formhelper/form_group.html
formhelper/templates/formhelper/formset.html
formhelper/templates/formhelper/formset_form.html
formhelper/templatetags/__init__.py
formhelper/templatetags/formhelper.py