Metadata-Version: 1.1
Name: django-formhelper
Version: 0.2
Summary: Django FormHelper is a collection of templates and templatetags to ease the pain in building out web forms
Home-page: http://github.com/bendavis78
Author: Ben Davis
Author-email: bendavis78@gmail.com
License: UNKNOWN
Keywords: django forms
Platform: UNKNOWN
Classifier: Development Status :: 4 - Beta
Classifier: Intended Audience :: Developers
Classifier: Operating System :: OS Independent
Classifier: Programming Language :: Python
Classifier: Topic :: Software Development :: Libraries :: Python Modules
